sfe/Cal_Comb.py
sfe/Element.py
sfe/Element_Type.py
sfe/Node.py
sfe/__init__.py
sfe/figure.py
sfe/solve.py
sfe-1.0.5.dist-info/LICENSE.txt
sfe-1.0.5.dist-info/METADATA
sfe-1.0.5.dist-info/WHEEL
sfe-1.0.5.dist-info/top_level.txt
sfe-1.0.5.dist-info/RECORD
