Metadata-Version: 2.1
Name: sfe
Version: 1.0.5
Summary: Python and finite Elements
Home-page: https://gitee.com/yonvone/sfe.git
Author: haoy_zhang
Author-email: haoy.zhang@foxmail.com
License: UNKNOWN
Platform: UNKNOWN
Classifier: Programming Language :: Python :: 3.6
Classifier: License :: OSI Approved :: MIT License
Classifier: Operating System :: OS Independent
Requires-Python: >=3.6
License-File: LICENSE.txt
Provides-Extra: sfe
Requires-Dist: python ; extra == 'sfe'
